setup.py
line_graph/Linegraph.py
line_graph/Preparedata.py
line_graph/__init__.py
line_graph.egg-info/PKG-INFO
line_graph.egg-info/SOURCES.txt
line_graph.egg-info/dependency_links.txt
line_graph.egg-info/not-zip-safe
line_graph.egg-info/top_level.txt