Metadata-Version: 1.0
Name: line-graph
Version: 1.3
Summary: Line graph for time series
Home-page: UNKNOWN
Author: Loredana Fattorini
Author-email: loredana.fattorini90@gmail.com
License: UNKNOWN
Platform: UNKNOWN
